{
    "graph_version": "0.6.0",
    "id": "pageviews_mobile_target_stacked",
    "slug": "pageviews_mobile_target_stacked",
    "name": "Mobile Page Views - Projections and Targets",
    "shortName": "Mobile Page Views",
    
    "desc" : "For Jun 12-Dec 12, Mobile Web and Zero views are Actuals; from Jan 13-Jun 13, they are projections (mobile web based on organic growth)",
    
    "root": {
        "nodeType": "canvas",
        
        "width": "auto",
        "height": 500,
        "xPadding": 0.001,
        "yPadding": 0.185,
        
        "children": [
            {
                "nodeType": "axis",
                "options": {
                    "orient": "bottom",
                    "dimension": "x"
                }
            },
            {
                "nodeType": "axis",
                "options": {
                    "orient": "left",
                    "dimension": "y"
                }
            },
            {
                "nodeType": "legend",
                "options": {
                    "label" : "Legend",
                    "dateFormat" : "MMM YYYY"
                }
            },
            {
                "nodeType": "zoom-brush"
            },
            {
                "nodeType": "bar-group",
                "options": {
                    "palette": "category10",
                    "bands" : {
                        "padding": 0.4,
                        "outerPadding": 0
                    },
                    "stack": {
                        "enabled" : true
                    }
                },
                "children": [
                    {
                        "nodeType": "bar",
                        "metric": {
                            "source_id": "rc_page_requests_mobile_target",
                            "source_col": 1,
                            "type": "int",
                            "timespan": { "start": "2012/06", "end": null, "step": null }
                        },
                        "options": {
                            "label": "Mobile Web",
                            "fill": "#7EA8E8"
                        }
                    },
                    {
                        "nodeType": "bar",
                        "metric": {
                            "source_id": "rc_page_requests_mobile_target",
                            "source_col": 2,
                            "type": "int",
                            "timespan": { "start": "2012/06", "end": null, "step": null }
                        },
                        "options": {
                            "label": "Zero",
                            "fill": "#980011"
                        }
                    },
                    {
                        "nodeType": "bar",
                        "metric": {
                            "source_id": "rc_page_requests_mobile_target",
                            "source_col": 3,
                            "type": "int",
                            "timespan": { "start": "2012/06", "end": null, "step": null }
                        },
                        "options": {
                            "label": "Zero Gap",
                            "fill": "#FF6458"
                        }
                    }
                ]
            },
            {
                "nodeType": "line-group",
                "children": [
                    {
                        "nodeType": "line",
                        "metric": {
                            "source_id": "rc_page_requests_mobile_target",
                            "source_col": 4,
                            "type": "int",
                            "timespan": { "start": "2012/06", "end": null, "step": null }
                        },
                        "options": {
                            "label": "Targets",
                            "stroke": {
                                "color": "#0E625B"
                            }
                        }
                    }
                ]
            }
        ]
    }
}
